wagtail_inventory-3.2.dist-info/licenses/LICENSE
wagtailinventory/__init__.py
wagtailinventory/apps.py
wagtailinventory/helpers.py
wagtailinventory/models.py
wagtailinventory/views.py
wagtailinventory/wagtail_hooks.py
wagtailinventory/fixtures/test_blocks.json
wagtailinventory/management/__init__.py
wagtailinventory/management/commands/__init__.py
wagtailinventory/management/commands/block_inventory.py
wagtailinventory/migrations/0001_initial.py
wagtailinventory/migrations/0002_pageblock_unique_constraint.py
wagtailinventory/migrations/0003_pageblock_id_bigautofield.py
wagtailinventory/migrations/__init__.py
wagtailinventory/tests/__init__.py
wagtailinventory/tests/settings.py
wagtailinventory/tests/test_helpers.py
wagtailinventory/tests/test_models.py
wagtailinventory/tests/test_views.py
wagtailinventory/tests/test_wagtail_hooks.py
wagtailinventory/tests/urls.py
wagtailinventory/tests/testapp/__init__.py
wagtailinventory/tests/testapp/blocks.py
wagtailinventory/tests/testapp/models.py
wagtailinventory/tests/testapp/migrations/0001_initial.py
wagtailinventory/tests/testapp/migrations/0002_nested_stream_block_page.py
wagtailinventory/tests/testapp/migrations/0003_single_content_block_optional.py
wagtailinventory/tests/testapp/migrations/__init__.py
wagtail_inventory-3.2.dist-info/METADATA
wagtail_inventory-3.2.dist-info/WHEEL
wagtail_inventory-3.2.dist-info/top_level.txt
wagtail_inventory-3.2.dist-info/RECORD
