Metadata-Version: 2.4
Name: wagtail-inventory
Version: 3.2
Summary: Wagtail report to filter pages by block content
Author-email: CFPB <tech@cfpb.gov>
License: CC0
Project-URL: Homepage, https://github.com/cfpb/wagtail-inventory
Project-URL: Bug Reports, https://github.com/cfpb/wagtail-inventory/issues
Project-URL: Source, https://github.com/cfpb/wagtail-inventory
Classifier: Framework :: Django
Classifier: Framework :: Django :: 4.2
Classifier: Framework :: Django :: 5.0
Classifier: Framework :: Django :: 5.1
Classifier: Framework :: Wagtail
Classifier: Framework :: Wagtail :: 6
Classifier: License :: CC0 1.0 Universal (CC0 1.0) Public Domain Dedication
Classifier: License :: Public Domain
Classifier: Programming Language :: Python
Classifier: Programming Language :: Python :: 3
Classifier: Programming Language :: Python :: 3.10
Classifier: Programming Language :: Python :: 3.11
Classifier: Programming Language :: Python :: 3.12
Classifier: Programming Language :: Python :: 3.13
Requires-Python: >=3.10
License-File: LICENSE
Requires-Dist: tqdm<5,>=4.15.0
Requires-Dist: wagtail>=6.2
Provides-Extra: testing
Requires-Dist: coverage[toml]; extra == "testing"
Dynamic: license-file
